setup.py
moh_probability/Binomialdistribution.py
moh_probability/Gaussiandistribution.py
moh_probability/Generaldistribution.py
moh_probability/__init__.py
moh_probability.egg-info/PKG-INFO
moh_probability.egg-info/SOURCES.txt
moh_probability.egg-info/dependency_links.txt
moh_probability.egg-info/not-zip-safe
moh_probability.egg-info/top_level.txt