Metadata-Version: 1.0
Name: moh-probability
Version: 1.0
Summary: Gaussian and Binomial distributions
Home-page: UNKNOWN
Author: Mohamed Mahmoud
Author-email: moh2661978@gmail.com
License: UNKNOWN
Platform: UNKNOWN
